progressorx/__init__.py
progressorx/exceptions.py
progressorx/manager.py
progressorx/models.py
progressorx/store.py
progressorx/backends/__init__.py
progressorx/backends/memory.py
progressorx/backends/redis_store.py
progressorx/backends/sql_store.py
progressorx/examples/__init__.py
progressorx/examples/basic.py
progressorx/examples/fastapi.py
progressorx-0.1.0.dist-info/METADATA
progressorx-0.1.0.dist-info/WHEEL
progressorx-0.1.0.dist-info/licenses/LICENSE
progressorx-0.1.0.dist-info/RECORD
