Metadata-Version: 2.4
Name: progressorx
Version: 0.1.0
Summary: Lightweight task progress tracking with pluggable storage backends
Project-URL: Homepage, https://github.com/Vasiliy566/progressor
Project-URL: Issues, https://github.com/Vasiliy566/progressor/issues
Author-email: Vasiliy566 <vasyaisaev31@gmail.com>
License-Expression: MIT
License-File: LICENSE
Classifier: Operating System :: OS Independent
Classifier: Programming Language :: Python :: 3
Requires-Python: >=3.9
Provides-Extra: redis
Requires-Dist: redis; extra == 'redis'
